fawaris/__init__.py
fawaris/exceptions.py
fawaris/models.py
fawaris/sep10.py
fawaris/sep24.py
fawaris-0.1.38.dist-info/LICENSE
fawaris-0.1.38.dist-info/WHEEL
fawaris-0.1.38.dist-info/METADATA
fawaris-0.1.38.dist-info/RECORD
