Metadata-Version: 2.1
Name: fawaris
Version: 0.1.38
Summary: Async framework-agnostic Stellar Anchor interface
Home-page: https://github.com/yuriescl/fawaris-python
License: Apache License Version 2.0
Author: Yuri Escalianti
Author-email: yuriescl@gmail.com
Requires-Python: >=3.7,<4.0
Classifier: License :: Other/Proprietary License
Classifier: Programming Language :: Python :: 3
Classifier: Programming Language :: Python :: 3.10
Classifier: Programming Language :: Python :: 3.7
Classifier: Programming Language :: Python :: 3.8
Classifier: Programming Language :: Python :: 3.9
Requires-Dist: PyJWT (>=2.4,<3.0)
Requires-Dist: pydantic (>=1.0,<2.0)
Requires-Dist: stellar-sdk (>=7.0.1,<8.0.0)
Requires-Dist: typing-extensions (>=4.1.1,<5.0.0)
